countries/__init__.py
countries/all_countries.py
allcountries-0.0.1.dist-info/LICENSE
allcountries-0.0.1.dist-info/METADATA
allcountries-0.0.1.dist-info/WHEEL
allcountries-0.0.1.dist-info/top_level.txt
allcountries-0.0.1.dist-info/RECORD
