Metadata-Version: 2.1
Name: allcountries
Version: 0.0.1
Summary: This is simple package to help make country names and country code available in your application.
Home-page: https://github.com/cehstephen/allcountries
Author: Stephen Tete
Author-email: cehstephen@gmail.com
License: UNKNOWN
Project-URL: Bug Tracker, https://github.com/cehstephen/allcountries/issues
Platform: UNKNOWN
Classifier: Programming Language :: Python :: 3
Classifier: License :: OSI Approved :: MIT License
Classifier: Operating System :: OS Independent
Requires-Python: >=3.5
License-File: LICENSE
